eapy_python_sdk/__init__.py
eapy_python_sdk/_test.py
eapy_python_sdk-1.1.0.dist-info/METADATA
eapy_python_sdk-1.1.0.dist-info/RECORD
eapy_python_sdk-1.1.0.dist-info/WHEEL
eapy_python_sdk-1.1.0.dist-info/top_level.txt
