Metadata-Version: 2.1
Name: eapy-python-sdk
Version: 1.1.0
Summary: Eapy python sdk
Home-page: http://marcomendao.betacode.tech
Author: Marco Mendao
Author-email: mac.mendao@gmail.com
License: UNKNOWN
Platform: UNKNOWN
Requires-Dist: requests
